setup.py
babies/__init__.py
babies/db.py
babies/yaml.py
babies.egg-info/PKG-INFO
babies.egg-info/SOURCES.txt
babies.egg-info/dependency_links.txt
babies.egg-info/not-zip-safe
babies.egg-info/requires.txt
babies.egg-info/top_level.txt
bin/babies