Metadata-Version: 1.0
Name: babies
Version: 0.2
Summary: Watch shows and record your viewing history
Home-page: http://github.com/ohjames/babies
Author: James Pike
Author-email: github@chilon.net
License: MIT
Platform: UNKNOWN
